odoo/addons/stock_restrict_expiration_date/README.rst
odoo/addons/stock_restrict_expiration_date/__init__.py
odoo/addons/stock_restrict_expiration_date/__manifest__.py
odoo/addons/stock_restrict_expiration_date/i18n/fr.po
odoo/addons/stock_restrict_expiration_date/i18n/stock_restrict_expiration_date.pot
odoo/addons/stock_restrict_expiration_date/models/__init__.py
odoo/addons/stock_restrict_expiration_date/models/stock_move.py
odoo/addons/stock_restrict_expiration_date/models/stock_quant.py
odoo/addons/stock_restrict_expiration_date/models/stock_rule.py
odoo/addons/stock_restrict_expiration_date/readme/CONTRIBUTORS.rst
odoo/addons/stock_restrict_expiration_date/readme/DESCRIPTION.rst
odoo/addons/stock_restrict_expiration_date/static/description/icon.png
odoo/addons/stock_restrict_expiration_date/static/description/index.html
odoo/addons/stock_restrict_expiration_date/tests/__init__.py
odoo/addons/stock_restrict_expiration_date/tests/test_restrict_expiration_date.py
odoo/addons/stock_restrict_expiration_date/views/stock_picking_views.xml
odoo14_addon_stock_restrict_expiration_date-14.0.1.3.1.dist-info/METADATA
odoo14_addon_stock_restrict_expiration_date-14.0.1.3.1.dist-info/WHEEL
odoo14_addon_stock_restrict_expiration_date-14.0.1.3.1.dist-info/top_level.txt
odoo14_addon_stock_restrict_expiration_date-14.0.1.3.1.dist-info/RECORD
