Metadata-Version: 2.1
Name: odoo14-addon-stock_restrict_expiration_date
Version: 14.0.1.3.1
Summary: Add concept of restrict lot on stock move based on specific expiration date
Home-page: https://github.com/OCA/stock-logistics-workflow
Author: Akretion, Odoo Community Association (OCA)
Author-email: support@odoo-community.org
License: AGPL-3
Classifier: Programming Language :: Python
Classifier: Framework :: Odoo
Classifier: Framework :: Odoo :: 14.0
Classifier: License :: OSI Approved :: GNU Affero General Public License v3
Requires-Python: >=3.6
Requires-Dist: odoo <14.1dev,>=14.0a
